tspymfe/__init__.py
tspymfe/_detrend.py
tspymfe/_embed.py
tspymfe/_internal.py
tspymfe/_models.py
tspymfe/_orthopoly.py
tspymfe/_period.py
tspymfe/_summary.py
tspymfe/_surrogates.py
tspymfe/_utils.py
tspymfe/autocorr.py
tspymfe/freq_domain.py
tspymfe/general.py
tspymfe/global_stats.py
tspymfe/info_theory.py
tspymfe/landmarking.py
tspymfe/local_stats.py
tspymfe/model_based.py
tspymfe/randomize.py
tspymfe/scoring.py
tspymfe/stat_tests.py
tspymfe/tsmfe.py
tspymfe-0.0.7.dist-info/LICENSE
tspymfe-0.0.7.dist-info/METADATA
tspymfe-0.0.7.dist-info/WHEEL
tspymfe-0.0.7.dist-info/top_level.txt
tspymfe-0.0.7.dist-info/RECORD
