Metadata-Version: 2.1
Name: tspymfe
Version: 0.0.7
Summary: Univariate time-series expansion for Pymfe package
Home-page: https://github.com/FelSiq/ts-pymfe
Author: Felipe Siqueira
Author-email: fel.siqr@gmail.com
License: UNKNOWN
Platform: UNKNOWN
Classifier: Programming Language :: Python :: 3
Classifier: License :: OSI Approved :: MIT License
Classifier: Operating System :: OS Independent
Requires-Python: >=3.6
Requires-Dist: nolds
Requires-Dist: numpy
Requires-Dist: pymfe
Requires-Dist: statsmodels (>=0.12.2)
Requires-Dist: scipy
Requires-Dist: scikit-learn
Requires-Dist: matplotlib
Requires-Dist: arch
Requires-Dist: supersmoother
